mongodb_migrator/__init__.py
mongodb_migrator/cli.py
mongodb_migrator/core.py
tests/__init__.py
tests/conftest.py
tests/test_migrator.py
mongrate-0.0.5.dist-info/LICENSE
mongrate-0.0.5.dist-info/METADATA
mongrate-0.0.5.dist-info/WHEEL
mongrate-0.0.5.dist-info/entry_points.txt
mongrate-0.0.5.dist-info/top_level.txt
mongrate-0.0.5.dist-info/RECORD
