Metadata-Version: 2.1
Name: mongrate
Version: 0.0.5
Summary: A MongoDB migration tool.
Home-page: https://github.com/Happy-Kumar-Sharma/mongo-migrate
Author: Happy Sharma
Author-email: happycse54@gmail.com
Keywords: MongoDB Migration,mongodb-migrator,python mongodb module,best mongodb migration library
Classifier: Programming Language :: Python :: 3
Classifier: License :: OSI Approved :: MIT License
Classifier: Operating System :: OS Independent
Requires-Python: >=3.7
License-File: LICENSE
Requires-Dist: pymongo
Requires-Dist: click
Requires-Dist: pyyaml
